footprint/__init__.py
footprint/__main__.py
footprint/utils/__init__.py
footprint/utils/apis.py
footprint/utils/config.py
footprint/utils/emailVerif.py
footprint/utils/lookup.py
footprint/utils/printFuncs.py
footprint/utils/social.py
footprint/utils/table.py
footprint/utils/data/emails.blocklist
footprint_py-1.25.dist-info/LICENSE
footprint_py-1.25.dist-info/METADATA
footprint_py-1.25.dist-info/WHEEL
footprint_py-1.25.dist-info/entry_points.txt
footprint_py-1.25.dist-info/top_level.txt
footprint_py-1.25.dist-info/RECORD
