Metadata-Version: 2.1
Name: footprint-py
Version: 1.25
Summary: A python OSINT tool to discover and analyze the digital footprint of a targets email or username across millions of sites.
Home-page: https://github.com/Frikallo/footprint
Author: Noah Kay
Author-email: contact@noahkay.dev
License: Apache
Keywords: cli,email,osint
Platform: UNKNOWN
Classifier: License :: OSI Approved :: Apache Software License
Classifier: Programming Language :: Python
Classifier: Programming Language :: Python :: 3
Classifier: Programming Language :: Python :: 3.6
Classifier: Programming Language :: Python :: 3.7
Classifier: Programming Language :: Python :: 3.8
Classifier: Programming Language :: Python :: 3.9
Classifier: Programming Language :: Python :: 3.10
Classifier: Programming Language :: Python :: 3.11
Classifier: Operating System :: Microsoft :: Windows
Classifier: Operating System :: POSIX :: Linux
Requires-Python: >=3.6
License-File: LICENSE
Requires-Dist: halo (==0.0.31)
Requires-Dist: email-validator (==1.3.0)
Requires-Dist: dnspython (==2.3.0)
Requires-Dist: pyfiglet (==0.8.post1)
Requires-Dist: termcolor (==2.2.0)
Requires-Dist: requests (==2.28.2)
